{
    "placements": [
        {
            "x": 817,
            "y": 598
        },
        {
            "x": 817,
            "y": 608
        },
        {
            "x": 817,
            "y": 618
        },
        {
            "x": 817,
            "y": 628
        },
        {
            "x": 889,
            "y": 795
        },
        {
            "x": 727.5,
            "y": 795
        },
        {
            "x": 817,
            "y": 758
        },
        {
            "x": 939,
            "y": 651.5
        },
        {
            "x": 773.75,
            "y": 786.4889767347254
        },
        {
            "x": 735.6602550378444,
            "y": 645
        },
        {
            "x": 832.75,
            "y": 546.5110232652746
        },
        {
            "x": 727,
            "y": 590
        },
        {
            "x": 893,
            "y": 546.6602550378444
        },
        {
            "x": 817,
            "y": 698
        },
        {
            "x": 939,
            "y": 712
        },
        {
            "x": 735.6602550378444,
            "y": 746
        },
        {
            "x": 735.6602550378444,
            "y": 675
        },
        {
            "x": 727,
            "y": 690
        },
        {
            "x": 727,
            "y": 784
        },
        {
            "x": 727,
            "y": 751
        },
        {
            "x": 863,
            "y": 546.6602550378444
        },
        {
            "x": 727,
            "y": 650
        },
        {
            "x": 817,
            "y": 708
        },
        {
            "x": 939,
            "y": 753.5
        },
        {
            "x": 923.25,
            "y": 546.5110232652746
        },
        {
            "x": 727,
            "y": 680
        },
        {
            "x": 839,
            "y": 795
        },
        {
            "x": 727,
            "y": 761
        },
        {
            "x": 939,
            "y": 591.5
        },
        {
            "x": 827,
            "y": 618
        },
        {
            "x": 939,
            "y": 641.5
        },
        {
            "x": 939,
            "y": 621.5
        },
        {
            "x": 817,
            "y": 718
        },
        {
            "x": 939,
            "y": 763.5
        },
        {
            "x": 898,
            "y": 538
        },
        {
            "x": 735.6602550378444,
            "y": 756
        },
        {
            "x": 838,
            "y": 538
        },
        {
            "x": 939,
            "y": 611.5
        },
        {
            "x": 817,
            "y": 668
        },
        {
            "x": 777,
            "y": 538
        },
        {
            "x": 779,
            "y": 795
        },
        {
            "x": 735.5110232652746,
            "y": 725.75
        },
        {
            "x": 939,
            "y": 681.5
        },
        {
            "x": 737.5,
            "y": 795
        },
        {
            "x": 827,
            "y": 568
        },
        {
            "x": 899,
            "y": 795
        },
        {
            "x": 827,
            "y": 638
        },
        {
            "x": 737,
            "y": 538
        },
        {
            "x": 930.8184649140233,
            "y": 727.75
        },
        {
            "x": 727,
            "y": 610
        },
        {
            "x": 809,
            "y": 795
        },
        {
            "x": 727,
            "y": 741
        },
        {
            "x": 827,
            "y": 598
        },
        {
            "x": 939,
            "y": 601.5
        },
        {
            "x": 727,
            "y": 548.5
        },
        {
            "x": 735.000001,
            "y": 778
        },
        {
            "x": 939,
            "y": 773.5
        },
        {
            "x": 819,
            "y": 795
        },
        {
            "x": 928.5,
            "y": 538
        },
        {
            "x": 854,
            "y": 786.3397449621556
        },
        {
            "x": 817.5,
            "y": 538
        },
        {
            "x": 930.648352455755,
            "y": 576
        },
        {
            "x": 735.6602550378444,
            "y": 695
        },
        {
            "x": 827.5,
            "y": 538
        },
        {
            "x": 869,
            "y": 795
        },
        {
            "x": 939,
            "y": 631.5
        },
        {
            "x": 894,
            "y": 786.3397449621556
        },
        {
            "x": 817,
            "y": 688
        },
        {
            "x": 747,
            "y": 538
        },
        {
            "x": 879,
            "y": 795
        },
        {
            "x": 939,
            "y": 539
        },
        {
            "x": 787,
            "y": 538
        },
        {
            "x": 757,
            "y": 538
        },
        {
            "x": 939,
            "y": 702
        },
        {
            "x": 727,
            "y": 670
        },
        {
            "x": 807,
            "y": 538
        },
        {
            "x": 827,
            "y": 628
        },
        {
            "x": 804,
            "y": 786.3397449621556
        },
        {
            "x": 789,
            "y": 795
        },
        {
            "x": 939,
            "y": 549
        },
        {
            "x": 858,
            "y": 538
        },
        {
            "x": 753,
            "y": 786.648352455755
        },
        {
            "x": 849,
            "y": 795
        },
        {
            "x": 812.25,
            "y": 546.5110232652746
        },
        {
            "x": 827,
            "y": 608
        },
        {
            "x": 727,
            "y": 600
        },
        {
            "x": 735.6602550378444,
            "y": 736
        },
        {
            "x": 735.6602550378444,
            "y": 655
        },
        {
            "x": 918,
            "y": 538
        },
        {
            "x": 727,
            "y": 640
        },
        {
            "x": 919,
            "y": 795
        },
        {
            "x": 934,
            "y": 786.3397449621556
        },
        {
            "x": 817,
            "y": 678
        },
        {
            "x": 930.8184649140233,
            "y": 564.75
        },
        {
            "x": 772,
            "y": 546.6602550378444
        },
        {
            "x": 878,
            "y": 538
        },
        {
            "x": 735.5110232652746,
            "y": 584.75
        },
        {
            "x": 817,
            "y": 738
        },
        {
            "x": 859,
            "y": 795
        },
        {
            "x": 758.5,
            "y": 795
        },
        {
            "x": 727,
            "y": 772
        },
        {
            "x": 939,
            "y": 661.5
        },
        {
            "x": 799,
            "y": 795
        },
        {
            "x": 939,
            "y": 795
        },
        {
            "x": 727,
            "y": 538
        },
        {
            "x": 727,
            "y": 559.5
        },
        {
            "x": 848,
            "y": 538
        },
        {
            "x": 939,
            "y": 581.5
        },
        {
            "x": 930.3397449621556,
            "y": 697
        },
        {
            "x": 868,
            "y": 538
        },
        {
            "x": 909,
            "y": 795
        },
        {
            "x": 727,
            "y": 710.5
        },
        {
            "x": 742,
            "y": 546.6602550378444
        },
        {
            "x": 727,
            "y": 731
        },
        {
            "x": 929,
            "y": 795
        },
        {
            "x": 939,
            "y": 743.5
        },
        {
            "x": 817,
            "y": 728
        },
        {
            "x": 908,
            "y": 538
        },
        {
            "x": 883,
            "y": 546.6602550378444
        },
        {
            "x": 768.5,
            "y": 795
        },
        {
            "x": 735.5110232652746,
            "y": 705.25
        },
        {
            "x": 735.6602550378444,
            "y": 625
        },
        {
            "x": 727,
            "y": 579.5
        },
        {
            "x": 817,
            "y": 648
        },
        {
            "x": 817,
            "y": 638
        },
        {
            "x": 727,
            "y": 620
        },
        {
            "x": 939,
            "y": 671.5
        },
        {
            "x": 827,
            "y": 578
        },
        {
            "x": 747.5,
            "y": 795
        },
        {
            "x": 939,
            "y": 722
        },
        {
            "x": 888,
            "y": 538
        },
        {
            "x": 727,
            "y": 720.5
        },
        {
            "x": 939,
            "y": 692
        },
        {
            "x": 727,
            "y": 700
        },
        {
            "x": 727,
            "y": 569.5
        },
        {
            "x": 939,
            "y": 559
        },
        {
            "x": 727,
            "y": 630
        },
        {
            "x": 930.4889767347254,
            "y": 686.75
        },
        {
            "x": 817,
            "y": 748
        },
        {
            "x": 735.351647544245,
            "y": 766.5
        },
        {
            "x": 827,
            "y": 588
        },
        {
            "x": 817,
            "y": 658
        },
        {
            "x": 797,
            "y": 538
        },
        {
            "x": 939,
            "y": 733.5
        },
        {
            "x": 829,
            "y": 795
        },
        {
            "x": 767,
            "y": 538
        },
        {
            "x": 727,
            "y": 660
        },
        {
            "x": 939,
            "y": 570.5
        },
        {
            "x": 827,
            "y": 648
        }
    ]
}